rapidocr_web/__init__.py
rapidocr_web/ocrweb.py
rapidocr_web/task.py
rapidocr_web/static/css/favicon.ico
rapidocr_web/static/css/main.css
rapidocr_web/static/js/app.js
rapidocr_web/static/js/jquery-3.0.0.min.js
rapidocr_web/templates/index.html
rapidocr_web-1.0.0.dist-info/licenses/LICENSE
rapidocr_web-1.0.0.dist-info/METADATA
rapidocr_web-1.0.0.dist-info/WHEEL
rapidocr_web-1.0.0.dist-info/entry_points.txt
rapidocr_web-1.0.0.dist-info/top_level.txt
rapidocr_web-1.0.0.dist-info/RECORD
