Metadata-Version: 2.4
Name: rapidocr_web
Version: 1.0.0
Summary: The Web version of RapidOCR
Home-page: https://github.com/RapidAI/RapidOCRWeb
Download-URL: https://github.com/RapidAI/RapidOCRWeb.git
Author: SWHL
Author-email: liekkaskono@163.com
License: Apache-2.0
Keywords: ocr,text_detection,text_recognition,db,onnxruntime,paddleocr,openvino,rapidocr
Platform: Any
Classifier: Programming Language :: Python :: 3.6
Classifier: Programming Language :: Python :: 3.7
Classifier: Programming Language :: Python :: 3.8
Classifier: Programming Language :: Python :: 3.9
Classifier: Programming Language :: Python :: 3.10
Classifier: Programming Language :: Python :: 3.11
Classifier: Programming Language :: Python :: 3.12
Classifier: Programming Language :: Python :: 3.13
Requires-Python: >=3.6
License-File: LICENSE
Requires-Dist: requests
Requires-Dist: Flask>=2.1.0
Requires-Dist: rapidocr_onnxruntime
Dynamic: author
Dynamic: author-email
Dynamic: classifier
Dynamic: description
Dynamic: description-content-type
Dynamic: download-url
Dynamic: home-page
Dynamic: keywords
Dynamic: license
Dynamic: license-file
Dynamic: platform
Dynamic: requires-dist
Dynamic: requires-python
Dynamic: summary
